infraflow/__init__.py
infraflow/runtime/__init__.py
infraflow/runtime/common/__init__.py
infraflow/runtime/common/task_tracker.py
infraflow/runtime/docker/__init__.py
infraflow/runtime/docker/contracts/__init__.py
infraflow/runtime/docker/contracts/common.py
infraflow/runtime/docker/contracts/sqs.py
infraflow/runtime/docker/patterns/__init__.py
infraflow/runtime/docker/patterns/sqs_parallel_process.py
infraflow/runtime/lambdas/__init__.py
infraflow/runtime/lambdas/events/__init__.py
infraflow/runtime/lambdas/events/common.py
infraflow/runtime/lambdas/events/http.py
infraflow/runtime/lambdas/events/sqs.py
infraflow/runtime/lambdas/handlers/__init__.py
infraflow/runtime/lambdas/handlers/http.py
infraflow/runtime/lambdas/handlers/sqs.py
py_infraflow_runtime_aws-0.1.2.dist-info/METADATA
py_infraflow_runtime_aws-0.1.2.dist-info/WHEEL
py_infraflow_runtime_aws-0.1.2.dist-info/RECORD
